transkribus/__init__.py
transkribus/admin.py
transkribus/apps.py
transkribus/config.py
transkribus/models.py
transkribus/tests.py
transkribus/trp_utils.py
transkribus/urls.py
transkribus/views.py
transkribus/templates/transkribus/doc_overview.html
transkribus/templates/transkribus/documents.html
transkribus/templates/transkribus/hits.html
transkribus/templates/transkribus/page.html
transkribus/templates/transkribus/search.html
transkribus/templatetags/__init__.py
transkribus/templatetags/transkribus_extras.py
acdh_django_transkribus-1.1.0.dist-info/LICENSE
acdh_django_transkribus-1.1.0.dist-info/METADATA
acdh_django_transkribus-1.1.0.dist-info/WHEEL
acdh_django_transkribus-1.1.0.dist-info/top_level.txt
acdh_django_transkribus-1.1.0.dist-info/RECORD
