Metadata-Version: 2.1
Name: acdh-django-transkribus
Version: 1.1.0
Summary: django app for interacting with the Transkribus-API
Home-page: https://github.com/acdh-oeaw/acdh-django-transkribus
Author: Peter Andorfer, Ingo Börner
Author-email: peter.andorfer@oeaw.ac.at, ingo.boerner@oeaw.ac.at
License: MIT
Keywords: acdh-django-transkribus
Platform: UNKNOWN
Classifier: Development Status :: 3 - Alpha
Classifier: Framework :: Django :: 2.0
Classifier: Intended Audience :: Developers
Classifier: License :: OSI Approved :: BSD License
Classifier: Natural Language :: English
Classifier: Programming Language :: Python :: 3
Classifier: Programming Language :: Python :: 3.4
Classifier: Programming Language :: Python :: 3.5
Classifier: Programming Language :: Python :: 3.6
Requires-Dist: requests
Requires-Dist: lxml
Requires-Dist: django
